package_upload_test/test1.py
package_upload_test/test2.py
package_upload_test-0.0.0.1.dist-info/METADATA
package_upload_test-0.0.0.1.dist-info/WHEEL
package_upload_test-0.0.0.1.dist-info/top_level.txt
package_upload_test-0.0.0.1.dist-info/RECORD
